LICENSE
MANIFEST.in
README.rst
korpus.py
requirements.txt
runtests.sh
setup.py
test_korpus.py
korpus.egg-info/PKG-INFO
korpus.egg-info/SOURCES.txt
korpus.egg-info/dependency_links.txt
korpus.egg-info/top_level.txt