Metadata-Version: 1.0
Name: korpus
Version: 0.0.1
Summary: similarity made easy!
Home-page: https://github.com/metglobal/korpus
Author: Metglobal
Author-email: kadir.pekel@metglobal.com
License: MIT
Platform: UNKNOWN
